LICENSE.txt
README.md
setup.cfg
setup.py
badsql/__init__.py
badsql/db.py
badsql.egg-info/PKG-INFO
badsql.egg-info/SOURCES.txt
badsql.egg-info/dependency_links.txt
badsql.egg-info/entry_points.txt
badsql.egg-info/top_level.txt