Metadata-Version: 2.1
Name: badsql
Version: 1.3.1
Summary: SQL but worse
Home-page: https://github.com/nayakrujul/badsql
Author: Rujul Nayak
Author-email: rujulnayak@outlook.com
License: MIT
Download-URL: https://github.com/nayakrujul/badsql/archive/refs/tags/v_01.tar.gz
Keywords: database,SQL,file
Platform: UNKNOWN
Classifier: Development Status :: 3 - Alpha
Classifier: Intended Audience :: Developers
Classifier: Topic :: Software Development :: Build Tools
Classifier: License :: OSI Approved :: MIT License
Classifier: Programming Language :: Python :: 3
Classifier: Programming Language :: Python :: 3.4
Classifier: Programming Language :: Python :: 3.5
Classifier: Programming Language :: Python :: 3.6
Classifier: Programming Language :: Python :: 3.7
Classifier: Programming Language :: Python :: 3.8
Classifier: Programming Language :: Python :: 3.9
License-File: LICENSE.txt
